bossy
