Metadata-Version: 1.0
Name: bossy
Version: 0.0.2
Summary: Write commands in Python, run them from the shell.
Home-page: http://github.com/zacharyvoase/bossy
Author: Zachary Voase
Author-email: z@zacharyvoase.com
License: UNKNOWN
Platform: UNKNOWN
